MANIFEST.in
setup.cfg
setup.py
Genetic/GA.py
Genetic/__init__.py
Genetic/crossover.py
Genetic/fitness.py
Genetic/individual.py
Genetic/mutation.py
Genetic/population.py
Genetic/selection.py
Genetic/settings.py
Genetic/setup.py
Genetic/visualization.py
Pyvolution.egg-info/PKG-INFO
Pyvolution.egg-info/SOURCES.txt
Pyvolution.egg-info/dependency_links.txt
Pyvolution.egg-info/not-zip-safe
Pyvolution.egg-info/top_level.txt