Metadata-Version: 1.1
Name: Pyvolution
Version: 1.1
Summary: Evolutionary Algorithms Framework
Home-page: https://github.com/inspectorG4dget/Genetic-Framework
Author: Ashwin Panchapakesan
Author-email: ashwin.panchapakesan@gmail.com
License: Apache License, Version 2.0
Platform: UNKNOWN
Classifier: Development Status :: 5 - Production/Stable
Classifier: Intended Audience :: Developers
Classifier: Natural Language :: English
Classifier: Programming Language :: Python
Classifier: Programming Language :: Python :: 2.7
